{"analysis": {"adg": 0.002241010390366714,
              "drawdown_worst": 0.21524638903918256,
              "equity_balance_diff_max": 0.16493237594368437,
              "equity_balance_diff_mean": 0.001835781645691759,
              "loss_profit_ratio": 0.29394662279882133,
              "mdg": 0.0012194597337385935,
              "n_iters": 36894,
              "sharpe_ratio": 0.22407277810808288,
              "w_0": -0.0012194597337385935,
              "w_1": -0.22407277810808288},
 "backtest": {"base_dir": "backtests",
              "end_date": "2024-10-18",
              "exchange": "bybit",
              "start_date": "2021-10-01",
              "starting_balance": 100000,
              "symbols": ["10000000AIDOGEUSDT",
                          "1000000BABYDOGEUSDT",
                          "1000000MOGUSDT",
                          "1000000PEIPEIUSDT",
                          "10000COQUSDT",
                          "10000LADYSUSDT",
                          "10000SATSUSDT",
                          "10000WENUSDT",
                          "10000WHYUSDT",
                          "1000APUUSDT",
                          "1000BONKUSDT",
                          "1000BTTUSDT",
                          "1000CATSUSDT",
                          "1000CATUSDT",
                          "1000FLOKIUSDT",
                          "1000LUNCUSDT",
                          "1000MUMUUSDT",
                          "1000NEIROCTOUSDT",
                          "1000PEPEUSDT",
                          "1000RATSUSDT",
                          "1000TURBOUSDT",
                          "1000XECUSDT",
                          "1CATUSDT",
                          "1INCHUSDT",
                          "A8USDT",
                          "AAVEUSDT",
                          "ACEUSDT",
                          "ACHUSDT",
                          "ADAUSDT",
                          "AERGOUSDT",
                          "AEROUSDT",
                          "AEVOUSDT",
                          "AGIUSDT",
                          "AGLDUSDT",
                          "AIOZUSDT",
                          "AIUSDT",
                          "AKROUSDT",
                          "AKTUSDT",
                          "ALEOUSDT",
                          "ALGOUSDT",
                          "ALICEUSDT",
                          "ALPACAUSDT",
                          "ALPHAUSDT",
                          "ALTUSDT",
                          "AMBUSDT",
                          "ANKRUSDT",
                          "APEUSDT",
                          "API3USDT",
                          "APTUSDT",
                          "ARBUSDT",
                          "ARKMUSDT",
                          "ARKUSDT",
                          "ARPAUSDT",
                          "ARUSDT",
                          "ASTRUSDT",
                          "ATAUSDT",
                          "ATHUSDT",
                          "ATOMUSDT",
                          "AUCTIONUSDT",
                          "AUDIOUSDT",
                          "AVAILUSDT",
                          "AVAXUSDT",
                          "AXLUSDT",
                          "AXSUSDT",
                          "BADGERUSDT",
                          "BAKEUSDT",
                          "BALUSDT",
                          "BANANAUSDT",
                          "BANDUSDT",
                          "BATUSDT",
                          "BBUSDT",
                          "BCHUSDT",
                          "BEAMUSDT",
                          "BELUSDT",
                          "BENDOGUSDT",
                          "BICOUSDT",
                          "BIGTIMEUSDT",
                          "BLASTUSDT",
                          "BLURUSDT",
                          "BLZUSDT",
                          "BNBUSDT",
                          "BNTUSDT",
                          "BNXUSDT",
                          "BOBAUSDT",
                          "BOMEUSDT",
                          "BONDUSDT",
                          "BRETTUSDT",
                          "BSVUSDT",
                          "BSWUSDT",
                          "BTCUSDT",
                          "C98USDT",
                          "CAKEUSDT",
                          "CARVUSDT",
                          "CATIUSDT",
                          "CELOUSDT",
                          "CELRUSDT",
                          "CETUSUSDT",
                          "CFXUSDT",
                          "CHESSUSDT",
                          "CHRUSDT",
                          "CHZUSDT",
                          "CKBUSDT",
                          "CLOUDUSDT",
                          "COMBOUSDT",
                          "COMPUSDT",
                          "COREUSDT",
                          "COSUSDT",
                          "COTIUSDT",
                          "CROUSDT",
                          "CRVUSDT",
                          "CTCUSDT",
                          "CTKUSDT",
                          "CTSIUSDT",
                          "CVCUSDT",
                          "CVXUSDT",
                          "CYBERUSDT",
                          "DARUSDT",
                          "DASHUSDT",
                          "DATAUSDT",
                          "DBRUSDT",
                          "DEEPUSDT",
                          "DEGENUSDT",
                          "DENTUSDT",
                          "DEXEUSDT",
                          "DGBUSDT",
                          "DODOUSDT",
                          "DOGEUSDT",
                          "DOGSUSDT",
                          "DOGUSDT",
                          "DOP1USDT",
                          "DOTUSDT",
                          "DRIFTUSDT",
                          "DUSKUSDT",
                          "DYDXUSDT",
                          "DYMUSDT",
                          "EDUUSDT",
                          "EGLDUSDT",
                          "EIGENUSDT",
                          "ENAUSDT",
                          "ENJUSDT",
                          "ENSUSDT",
                          "EOSUSDT",
                          "ETCUSDT",
                          "ETHBTCUSDT",
                          "ETHFIUSDT",
                          "ETHUSDT",
                          "ETHWUSDT",
                          "FBUSDT",
                          "FDUSDUSDT",
                          "FIDAUSDT",
                          "FILUSDT",
                          "FIOUSDT",
                          "FIREUSDT",
                          "FITFIUSDT",
                          "FLMUSDT",
                          "FLOWUSDT",
                          "FLRUSDT",
                          "FLUXUSDT",
                          "FORTHUSDT",
                          "FOXYUSDT",
                          "FTMUSDT",
                          "FTNUSDT",
                          "FUNUSDT",
                          "FXSUSDT",
                          "GALAUSDT",
                          "GASUSDT",
                          "GFTUSDT",
                          "GLMRUSDT",
                          "GLMUSDT",
                          "GMEUSDT",
                          "GMTUSDT",
                          "GMXUSDT",
                          "GNOUSDT",
                          "GOATUSDT",
                          "GODSUSDT",
                          "GOMININGUSDT",
                          "GRASSUSDT",
                          "GRTUSDT",
                          "GTCUSDT",
                          "GUSDT",
                          "HBARUSDT",
                          "HFTUSDT",
                          "HIFIUSDT",
                          "HIGHUSDT",
                          "HMSTRUSDT",
                          "HNTUSDT",
                          "HOOKUSDT",
                          "HOTUSDT",
                          "HPOS10IUSDT",
                          "ICPUSDT",
                          "ICXUSDT",
                          "IDEXUSDT",
                          "IDUSDT",
                          "ILVUSDT",
                          "IMXUSDT",
                          "INJUSDT",
                          "IOSTUSDT",
                          "IOTAUSDT",
                          "IOTXUSDT",
                          "IOUSDT",
                          "JASMYUSDT",
                          "JOEUSDT",
                          "JSTUSDT",
                          "JTOUSDT",
                          "JUPUSDT",
                          "KASUSDT",
                          "KAVAUSDT",
                          "KDAUSDT",
                          "KEYUSDT",
                          "KLAYUSDT",
                          "KMNOUSDT",
                          "KNCUSDT",
                          "KSMUSDT",
                          "L3USDT",
                          "LAIUSDT",
                          "LDOUSDT",
                          "LEVERUSDT",
                          "LINAUSDT",
                          "LINKUSDT",
                          "LISTAUSDT",
                          "LITUSDT",
                          "LOOKSUSDT",
                          "LPTUSDT",
                          "LQTYUSDT",
                          "LRCUSDT",
                          "LSKUSDT",
                          "LTCUSDT",
                          "LTOUSDT",
                          "LUNA2USDT",
                          "MAGICUSDT",
                          "MANAUSDT",
                          "MANEKIUSDT",
                          "MANTAUSDT",
                          "MASAUSDT",
                          "MASKUSDT",
                          "MAVIAUSDT",
                          "MAVUSDT",
                          "MAXUSDT",
                          "MBLUSDT",
                          "MBOXUSDT",
                          "MDTUSDT",
                          "MEMEUSDT",
                          "MERLUSDT",
                          "METISUSDT",
                          "MEWUSDT",
                          "MINAUSDT",
                          "MKRUSDT",
                          "MNTUSDT",
                          "MOBILEUSDT",
                          "MOCAUSDT",
                          "MONUSDT",
                          "MOODENGUSDT",
                          "MOTHERUSDT",
                          "MOVRUSDT",
                          "MTLUSDT",
                          "MYRIAUSDT",
                          "MYROUSDT",
                          "NEARUSDT",
                          "NEIROETHUSDT",
                          "NEOUSDT",
                          "NFPUSDT",
                          "NKNUSDT",
                          "NMRUSDT",
                          "NOTUSDT",
                          "NTRNUSDT",
                          "NULSUSDT",
                          "NYANUSDT",
                          "OGNUSDT",
                          "OGUSDT",
                          "OMGUSDT",
                          "OMNIUSDT",
                          "OMUSDT",
                          "ONDOUSDT",
                          "ONEUSDT",
                          "ONGUSDT",
                          "ONTUSDT",
                          "OPUSDT",
                          "ORBSUSDT",
                          "ORCAUSDT",
                          "ORDERUSDT",
                          "ORDIUSDT",
                          "OSMOUSDT",
                          "OXTUSDT",
                          "PAXGUSDT",
                          "PENDLEUSDT",
                          "PENGUSDT",
                          "PEOPLEUSDT",
                          "PERPUSDT",
                          "PHAUSDT",
                          "PHBUSDT",
                          "PIRATEUSDT",
                          "PIXELUSDT",
                          "PIXFIUSDT",
                          "POLUSDT",
                          "POLYXUSDT",
                          "PONKEUSDT",
                          "POPCATUSDT",
                          "PORTALUSDT",
                          "POWRUSDT",
                          "PRCLUSDT",
                          "PRIMEUSDT",
                          "PROMUSDT",
                          "PUFFERUSDT",
                          "PYRUSDT",
                          "PYTHUSDT",
                          "QIUSDT",
                          "QNTUSDT",
                          "QTUMUSDT",
                          "QUICKUSDT",
                          "RADUSDT",
                          "RAREUSDT",
                          "RAYDIUMUSDT",
                          "RDNTUSDT",
                          "REEFUSDT",
                          "RENDERUSDT",
                          "RENUSDT",
                          "REQUSDT",
                          "REZUSDT",
                          "RIFUSDT",
                          "RLCUSDT",
                          "RONUSDT",
                          "ROSEUSDT",
                          "RPLUSDT",
                          "RSRUSDT",
                          "RSS3USDT",
                          "RUNEUSDT",
                          "RVNUSDT",
                          "SAFEUSDT",
                          "SAGAUSDT",
                          "SANDUSDT",
                          "SCAUSDT",
                          "SCRTUSDT",
                          "SCRUSDT",
                          "SCUSDT",
                          "SEIUSDT",
                          "SFPUSDT",
                          "SHIB1000USDT",
                          "SILLYUSDT",
                          "SKLUSDT",
                          "SLERFUSDT",
                          "SLFUSDT",
                          "SLPUSDT",
                          "SNTUSDT",
                          "SNXUSDT",
                          "SOLUSDT",
                          "SPECUSDT",
                          "SPELLUSDT",
                          "SSVUSDT",
                          "STEEMUSDT",
                          "STGUSDT",
                          "STMXUSDT",
                          "STORJUSDT",
                          "STPTUSDT",
                          "STRKUSDT",
                          "STXUSDT",
                          "SUIUSDT",
                          "SUNDOGUSDT",
                          "SUNUSDT",
                          "SUPERUSDT",
                          "SUSHIUSDT",
                          "SWEATUSDT",
                          "SXPUSDT",
                          "SYNUSDT",
                          "SYSUSDT",
                          "TAIKOUSDT",
                          "TAOUSDT",
                          "THETAUSDT",
                          "TIAUSDT",
                          "TLMUSDT",
                          "TNSRUSDT",
                          "TOKENUSDT",
                          "TOMIUSDT",
                          "TONUSDT",
                          "TRBUSDT",
                          "TRUUSDT",
                          "TRXUSDT",
                          "TUSDT",
                          "TWTUSDT",
                          "UMAUSDT",
                          "UNFIUSDT",
                          "UNIUSDT",
                          "USDCUSDT",
                          "USDEUSDT",
                          "USTCUSDT",
                          "UXLINKUSDT",
                          "VANRYUSDT",
                          "VELOUSDT",
                          "VETUSDT",
                          "VIDTUSDT",
                          "VOXELUSDT",
                          "VRAUSDT",
                          "VTHOUSDT",
                          "WAVESUSDT",
                          "WAXPUSDT",
                          "WIFUSDT",
                          "WLDUSDT",
                          "WOOUSDT",
                          "WUSDT",
                          "XAIUSDT",
                          "XCHUSDT",
                          "XCNUSDT",
                          "XEMUSDT",
                          "XLMUSDT",
                          "XMRUSDT",
                          "XNOUSDT",
                          "XRDUSDT",
                          "XRPUSDT",
                          "XTZUSDT",
                          "XVGUSDT",
                          "XVSUSDT",
                          "YFIUSDT",
                          "YGGUSDT",
                          "ZBCNUSDT",
                          "ZECUSDT",
                          "ZENUSDT",
                          "ZETAUSDT",
                          "ZEUSUSDT",
                          "ZILUSDT",
                          "ZKFUSDT",
                          "ZKJUSDT",
                          "ZKUSDT",
                          "ZROUSDT",
                          "ZRXUSDT"]},
 "bot": {"long": {"close_grid_markup_range": 0.0017334985768226235,
                  "close_grid_min_markup": 0.005904394538430715,
                  "close_grid_qty_pct": 0.9474287833575334,
                  "close_trailing_grid_ratio": -0.3572056474808142,
                  "close_trailing_qty_pct": 0.790997153978582,
                  "close_trailing_retracement_pct": 0.021061189357032287,
                  "close_trailing_threshold_pct": -0.03450237515156016,
                  "ema_span_0": 812.0674448417258,
                  "ema_span_1": 1092.4043225890427,
                  "entry_grid_double_down_factor": 1.4538494585639725,
                  "entry_grid_spacing_pct": 0.042241139986904,
                  "entry_grid_spacing_weight": 1.068819799066718,
                  "entry_initial_ema_dist": -0.01889559650583702,
                  "entry_initial_qty_pct": 0.0069601369627593284,
                  "entry_trailing_grid_ratio": -0.41859377827164423,
                  "entry_trailing_retracement_pct": 0.0386871748742764,
                  "entry_trailing_threshold_pct": 0.05075335048181249,
                  "filter_relative_volume_clip_pct": 0.3364042354325556,
                  "filter_rolling_window": 10,
                  "n_positions": 2,
                  "total_wallet_exposure_limit": 2,
                  "unstuck_close_pct": 0.043361133434876145,
                  "unstuck_ema_dist": -0.027630154648801024,
                  "unstuck_loss_allowance_pct": 0.020424672538323762,
                  "unstuck_threshold": 0.7863608381875248},
         "short": {"close_grid_markup_range": 0.010952670818324748,
                   "close_grid_min_markup": 0.007803387993273788,
                   "close_grid_qty_pct": 0.3902995725415139,
                   "close_trailing_grid_ratio": -0.012350904415043495,
                   "close_trailing_qty_pct": 0.5817088910451883,
                   "close_trailing_retracement_pct": 0.03133884045769473,
                   "close_trailing_threshold_pct": -0.07591300225681301,
                   "ema_span_0": 268.4591240524118,
                   "ema_span_1": 649.4854900947578,
                   "entry_grid_double_down_factor": 2.9658284691695207,
                   "entry_grid_spacing_pct": 0.041888229242951804,
                   "entry_grid_spacing_weight": 9.560968813103853,
                   "entry_initial_ema_dist": -0.09504015250897568,
                   "entry_initial_qty_pct": 0.08047430980817728,
                   "entry_trailing_grid_ratio": 0.34265179993133515,
                   "entry_trailing_retracement_pct": 0.002852895748197533,
                   "entry_trailing_threshold_pct": -0.011841549229232981,
                   "filter_relative_volume_clip_pct": 0.6847017473984679,
                   "filter_rolling_window": 0,
                   "n_positions": 0,
                   "total_wallet_exposure_limit": 0,
                   "unstuck_close_pct": 0.08526619847679051,
                   "unstuck_ema_dist": -0.08139612898121347,
                   "unstuck_loss_allowance_pct": 0.0296104049999748,
                   "unstuck_threshold": 0.405720126886561}},
 "live": {"approved_coins": [],
          "auto_gs": true,
          "coin_flags": {},
          "empty_means_all_approved": false,
          "execution_delay_seconds": 2,
          "filter_by_min_effective_cost": true,
          "forced_mode_long": "",
          "forced_mode_short": "",
          "ignored_coins": [],
          "leverage": 10,
          "max_n_cancellations_per_batch": 5,
          "max_n_creations_per_batch": 3,
          "max_n_restarts_per_day": 10,
          "minimum_coin_age_days": 90,
          "ohlcvs_1m_rolling_window_days": 4,
          "ohlcvs_1m_update_after_minutes": 10,
          "pnls_max_lookback_days": 30,
          "price_distance_threshold": 0.002,
          "time_in_force": "good_till_cancelled",
          "user": "bybit_01"},
 "lock_filepath": "optimize_results/2024-10-21T11_06_52_373_coins_0c6e97df_all_results.txt.lock",
 "optimize": {"bounds": {"long_close_grid_markup_range": [0, 0.03],
                         "long_close_grid_min_markup": [0.001, 0.03],
                         "long_close_grid_qty_pct": [0.05, 1],
                         "long_close_trailing_grid_ratio": [-1, 1],
                         "long_close_trailing_qty_pct": [0.05, 1],
                         "long_close_trailing_retracement_pct": [0, 0.1],
                         "long_close_trailing_threshold_pct": [-0.1, 0.1],
                         "long_ema_span_0": [200, 1440],
                         "long_ema_span_1": [200, 1440],
                         "long_entry_grid_double_down_factor": [0.1, 3],
                         "long_entry_grid_spacing_pct": [0.001, 0.12],
                         "long_entry_grid_spacing_weight": [0, 10],
                         "long_entry_initial_ema_dist": [-0.1, 0.003],
                         "long_entry_initial_qty_pct": [0.005, 0.1],
                         "long_entry_trailing_grid_ratio": [-1, 1],
                         "long_entry_trailing_retracement_pct": [0, 0.1],
                         "long_entry_trailing_threshold_pct": [-0.1, 0.1],
                         "long_filter_relative_volume_clip_pct": [0, 1],
                         "long_filter_rolling_window": [10, 10],
                         "long_n_positions": [2, 2],
                         "long_total_wallet_exposure_limit": [2, 2],
                         "long_unstuck_close_pct": [0.001, 0.1],
                         "long_unstuck_ema_dist": [-0.1, 0.01],
                         "long_unstuck_loss_allowance_pct": [0, 0.05],
                         "long_unstuck_threshold": [0.4, 0.95],
                         "short_close_grid_markup_range": [0, 0.03],
                         "short_close_grid_min_markup": [0.001, 0.03],
                         "short_close_grid_qty_pct": [0.05, 1],
                         "short_close_trailing_grid_ratio": [-1, 1],
                         "short_close_trailing_qty_pct": [0.05, 1],
                         "short_close_trailing_retracement_pct": [0, 0.1],
                         "short_close_trailing_threshold_pct": [-0.1, 0.1],
                         "short_ema_span_0": [200, 1440],
                         "short_ema_span_1": [200, 1440],
                         "short_entry_grid_double_down_factor": [0.1, 3],
                         "short_entry_grid_spacing_pct": [0.001, 0.12],
                         "short_entry_grid_spacing_weight": [0, 10],
                         "short_entry_initial_ema_dist": [-0.1, 0.003],
                         "short_entry_initial_qty_pct": [0.005, 0.1],
                         "short_entry_trailing_grid_ratio": [-1, 1],
                         "short_entry_trailing_retracement_pct": [0, 0.1],
                         "short_entry_trailing_threshold_pct": [-0.1, 0.1],
                         "short_filter_relative_volume_clip_pct": [0, 1],
                         "short_filter_rolling_window": [0, 0],
                         "short_n_positions": [0, 0],
                         "short_total_wallet_exposure_limit": [0, 0],
                         "short_unstuck_close_pct": [0.001, 0.1],
                         "short_unstuck_ema_dist": [-0.1, 0.01],
                         "short_unstuck_loss_allowance_pct": [0, 0.05],
                         "short_unstuck_threshold": [0.4, 0.95]},
              "crossover_probability": 0.7,
              "iters": 300000,
              "limits": {"lower_bound_drawdown_worst": 0.25,
                         "lower_bound_equity_balance_diff_mean": 0.01,
                         "lower_bound_loss_profit_ratio": 0.6},
              "mutation_probability": 0.2,
              "n_cpus": 6,
              "population_size": 500,
              "scoring": ["mdg", "sharpe_ratio"]},
 "results_filename": "optimize_results/2024-10-21T11_06_52_373_coins_0c6e97df_all_results.txt"}